ifileoperation/__init__.py
ifileoperation/errors.py
ifileoperation/fileoperator.py
ifileoperation/flags.py
ifileoperation/com/__init__.py
ifileoperation/com/common.py
ifileoperation/com/fileoperation.py
ifileoperation/com/fileoperationprogresssink.py
ifileoperation/com/filesysbinddata.py
ifileoperation/com/interfaces/__init__.py
ifileoperation/com/interfaces/ifileoperation.py
ifileoperation/com/interfaces/ifileoperationprogresssink.py
ifileoperation/com/interfaces/ifilesysbinddata.py
ifileoperation/com/interfaces/ishellitem.py
ifileoperation-1.2.6.dist-info/LICENSE
ifileoperation-1.2.6.dist-info/METADATA
ifileoperation-1.2.6.dist-info/WHEEL
ifileoperation-1.2.6.dist-info/top_level.txt
ifileoperation-1.2.6.dist-info/RECORD
