Metadata-Version: 2.1
Name: ifileoperation
Version: 1.2.6
Summary: Python wrapper for using Win32's IFileOperation for manipulating the filesystem.
Author: lojack5
License: BSD 3-Clause
Project-URL: Homepage, https://github.com/lojack5/IFileOperation
Project-URL: Bug Tracker, https://github.com/lojack5/IFileOperation/issues
Classifier: Intended Audience :: Developers
Classifier: Programming Language :: Python :: 3 :: Only
Classifier: Programming Language :: Python :: 3.11
Classifier: Programming Language :: Python :: Implementation :: CPython
Classifier: License :: OSI Approved :: BSD License
Classifier: Operating System :: Microsoft :: Windows
Classifier: Typing :: Typed
Requires-Python: >=3.11
License-File: LICENSE
Requires-Dist: comtypes (>=1.1.14)
Requires-Dist: pywin32 (>=305)
